hold_splitter/blender_script.py
hold_splitter/blender_utils.py
hold_splitter/cli.py
hold_splitter/core.py
hold_splitter/geometry.py
hold_splitter/hold_isolator.py
hold_splitter/main_script.py
hold_splitter/visualization.py
hold_splitter/wall_hold_splitter.py
hold_splitter-0.3.1.dist-info/METADATA
hold_splitter-0.3.1.dist-info/WHEEL
hold_splitter-0.3.1.dist-info/entry_points.txt
hold_splitter-0.3.1.dist-info/RECORD
