Metadata-Version: 2.1
Name: hold-splitter
Version: 0.3.1
Summary: クライミングウォールの平面を可視化するツール
Author: Maki
Author-email: sunwood.ai.labs@gmail.com
Requires-Python: >=3.10,<4.0
Classifier: Programming Language :: Python :: 3
Classifier: Programming Language :: Python :: 3.10
Classifier: Programming Language :: Python :: 3.11
Classifier: Programming Language :: Python :: 3.12
Requires-Dist: loguru (>=0.7.2,<0.8.0)
Requires-Dist: matplotlib (>=3.9.2,<4.0.0)
Requires-Dist: numpy (>=2.0.1,<3.0.0)
Requires-Dist: open3d (>=0.18.0,<0.19.0)
Requires-Dist: pymeshlab (>=2023.12.post1,<2024.0)
Requires-Dist: tqdm (>=4.64.1,<5.0.0)
